segmented_docstring/__init__.py
segmented_docstring/cli.py
segmented_docstring/combiner.py
segmented_docstring/config.py
segmented_docstring/splitter.py
segmented_docstrng-0.4.12.dist-info/METADATA
segmented_docstrng-0.4.12.dist-info/WHEEL
segmented_docstrng-0.4.12.dist-info/RECORD
