Metadata-Version: 2.3
Name: segmented_docstrng
Version: 0.4.12
Summary: Split and Combine python bare code and docstrings
Project-URL: Homepage, https://github.com/robin-collins/segmented_docstring
Project-URL: Bug Tracker, https://github.com/robin-collins/segmented_docstring/issues
Project-URL: Documentation, https://robin-collins.github.io/segmented_docstring/
Author-email: Robin Collins <robin@blackcat-it.com.au>
Classifier: Intended Audience :: Developers
Classifier: License :: OSI Approved :: MIT License
Classifier: Operating System :: OS Independent
Classifier: Programming Language :: Python :: 3
Classifier: Programming Language :: Python :: 3.7
Classifier: Programming Language :: Python :: 3.8
Classifier: Programming Language :: Python :: 3.9
Classifier: Programming Language :: Python :: 3.10
Classifier: Programming Language :: Python :: 3.11
Classifier: Topic :: System :: Logging
Requires-Python: >=3.7
